mlvtools/__init__.py
mlvtools/check_script.py
mlvtools/cmd.py
mlvtools/exception.py
mlvtools/export_pipeline.py
mlvtools/gen_dvc.py
mlvtools/helper.py
mlvtools/ipynb_to_dvc.py
mlvtools/ipynb_to_python.py
mlvtools/conf/__init__.py
mlvtools/conf/conf.py
mlvtools/diff/__init__.py
mlvtools/diff/parse.py
mlvtools/docstring_helpers/__init__.py
mlvtools/docstring_helpers/extract.py
mlvtools/docstring_helpers/parse.py
mlvtools/mlv_dvc/__init__.py
mlvtools/mlv_dvc/dvc_parser.py
mlvtools/templates/dvc-cmd.tpl
mlvtools/templates/ml-python.tpl
mlvtools/templates/pipeline-export.tpl
mlvtools-2.1.1.data/scripts/check_all_scripts_consistency
mlvtools-2.1.1.data/scripts/check_script_consistency
mlvtools-2.1.1.data/scripts/export_pipeline
mlvtools-2.1.1.data/scripts/gen_dvc
mlvtools-2.1.1.data/scripts/ipynb_to_dvc
mlvtools-2.1.1.data/scripts/ipynb_to_python
mlvtools-2.1.1.dist-info/LICENSE
mlvtools-2.1.1.dist-info/METADATA
mlvtools-2.1.1.dist-info/WHEEL
mlvtools-2.1.1.dist-info/top_level.txt
mlvtools-2.1.1.dist-info/RECORD
